disrpt_utils/__init__.py
disrpt_utils/process_underscore.py
disrpt_utils/setup.py
disrpt_utils-0.5.2.dist-info/METADATA
disrpt_utils-0.5.2.dist-info/WHEEL
disrpt_utils-0.5.2.dist-info/top_level.txt
disrpt_utils-0.5.2.dist-info/RECORD
