Metadata-Version: 2.1
Name: disrpt-utils
Version: 0.5.2
Summary: disrpt utils
Home-page: https://github.com/sileod/disrpt_utils/
Author: Damien Sileo
